README.md
setup.py
stns/__init__.py
stns/__version__.py
stns/deprec_guiapp.py
stns/detect.py
stns/modzscore.py
stns/scratch.py
stns/stimcalc.py
stns.egg-info/PKG-INFO
stns.egg-info/SOURCES.txt
stns.egg-info/dependency_links.txt
stns.egg-info/requires.txt
stns.egg-info/top_level.txt
stns/gui/__init__.py
stns/gui/dataentry.py
stns/gui/parameterentry.py
stns/gui/phase.py
stns/gui/selectchannel.py
stns/gui/spikedetectiongui.py
stns/gui/timeseries.py
stns/io/__init__.py
stns/io/load.py
stns/io/readcrabanalyzer.py
stns/model/__init__.py
stns/model/neuronparameters.py
stns/plot/__init__.py
stns/plot/crabanalyzerplotting.py
stns/plot/matplotlibmisc.py
stns/plot/scrollabletimeseries.py