Metadata-Version: 2.1
Name: stns
Version: 0.0.2
Summary: A collection of scripts used in the Nusbaum Lab for data analysis, modeling, and visualization
Home-page: https://github.com/LoganJF/crabby
Author: Logan Fickling
Author-email: loganfickling@gmail.com
License: UNKNOWN
Platform: UNKNOWN
Requires-Python: >=3.6.0
